odoo/addons/partner_title_order/README.rst
odoo/addons/partner_title_order/__init__.py
odoo/addons/partner_title_order/__manifest__.py
odoo/addons/partner_title_order/i18n/es.po
odoo/addons/partner_title_order/i18n/fr.po
odoo/addons/partner_title_order/i18n/it.po
odoo/addons/partner_title_order/i18n/partner_title_order.pot
odoo/addons/partner_title_order/models/__init__.py
odoo/addons/partner_title_order/models/res_partner_title.py
odoo/addons/partner_title_order/readme/CONTRIBUTORS.md
odoo/addons/partner_title_order/readme/CREDITS.md
odoo/addons/partner_title_order/readme/DESCRIPTION.md
odoo/addons/partner_title_order/static/description/icon.png
odoo/addons/partner_title_order/static/description/index.html
odoo/addons/partner_title_order/tests/__init__.py
odoo/addons/partner_title_order/tests/test_partner_title.py
odoo/addons/partner_title_order/views/res_partner_title_views.xml
odoo_addon_partner_title_order-18.0.1.0.0.5.dist-info/METADATA
odoo_addon_partner_title_order-18.0.1.0.0.5.dist-info/WHEEL
odoo_addon_partner_title_order-18.0.1.0.0.5.dist-info/top_level.txt
odoo_addon_partner_title_order-18.0.1.0.0.5.dist-info/RECORD
